sambinder/blastpr.zip
sambinder/sam_models.zip
sambinder/sambinder.py
sambinder/code/__init__.py
sambinder/code/fromfasta.py
sambinder/code/motif.py
sambinder/code/motif2bin.py
sambinder/code/normalise.py
sambinder/code/predict.py
sambinder/code/sambinder.py
sambinder/code/script
sambinder/code/seq2pssm_imp.py
sambinder-1.0.dist-info/LICENSE
sambinder-1.0.dist-info/METADATA
sambinder-1.0.dist-info/WHEEL
sambinder-1.0.dist-info/entry_points.txt
sambinder-1.0.dist-info/top_level.txt
sambinder-1.0.dist-info/RECORD
