Metadata-Version: 2.1
Name: sambinder
Version: 1.0
Summary: A tool for predicting S-adenosyl-L-methionine binding sites
Home-page: https://github.com/raghavagps/sambinder
Requires-Python: >=3.5, <=3.7
License-File: LICENSE
Requires-Dist: numpy
Requires-Dist: pandas
Requires-Dist: argparse
Requires-Dist: joblib
Requires-Dist: scikit-learn (==0.21.2)
